autoppt/__init__.py
autoppt/app.py
autoppt/config.py
autoppt/data_types.py
autoppt/exceptions.py
autoppt/generator.py
autoppt/llm_provider.py
autoppt/main.py
autoppt/ppt_renderer.py
autoppt/researcher.py
autoppt-0.3.0.dist-info/licenses/LICENSE
autoppt-0.3.0.dist-info/METADATA
autoppt-0.3.0.dist-info/WHEEL
autoppt-0.3.0.dist-info/entry_points.txt
autoppt-0.3.0.dist-info/top_level.txt
autoppt-0.3.0.dist-info/RECORD
