Metadata-Version: 2.4
Name: autoppt
Version: 0.3.0
Summary: Generate Professional Presentations in Seconds using AI
Author-email: Baohua <baohua@example.com>
Project-URL: Homepage, https://github.com/yeasy/autoppt
Project-URL: Bug Tracker, https://github.com/yeasy/autoppt/issues
Classifier: Programming Language :: Python :: 3
Classifier: License :: OSI Approved :: Apache Software License
Classifier: Operating System :: OS Independent
Classifier: Topic :: Office/Business :: Financial :: Spreadsheet
Classifier: Topic :: Multimedia :: Graphics :: Presentation
Requires-Python: >=3.8
License-File: LICENSE
Requires-Dist: python-pptx
Requires-Dist: pydantic
Requires-Dist: python-dotenv
Requires-Dist: requests
Requires-Dist: openai
Requires-Dist: google-genai
Requires-Dist: anthropic
Requires-Dist: ddgs
Requires-Dist: wikipedia
Requires-Dist: tqdm
Requires-Dist: streamlit
Dynamic: license-file
